academylib.py
academylib-1.0.1.dist-info/METADATA
academylib-1.0.1.dist-info/WHEEL
academylib-1.0.1.dist-info/top_level.txt
academylib-1.0.1.dist-info/RECORD
