Metadata-Version: 2.1
Name: academylib
Version: 1.0.1
Summary: Academy 4 Summer Course
